txeffect/__init__.py
txeffect/test_txeffect.py
txeffect-1.0.0.dist-info/METADATA
txeffect-1.0.0.dist-info/WHEEL
txeffect-1.0.0.dist-info/top_level.txt
txeffect-1.0.0.dist-info/RECORD
