Metadata-Version: 2.1
Name: txeffect
Version: 1.0.0
Summary: Effect/Twisted integration
Home-page: https://github.com/python-effect/txeffect/
Author: Christopher Armstrong
Author-email: UNKNOWN
License: MIT
Platform: UNKNOWN
Classifier: License :: OSI Approved :: MIT License
Classifier: Programming Language :: Python :: 2
Classifier: Programming Language :: Python :: 3
Requires-Dist: effect
Requires-Dist: twisted
